ctrlaltdata/__init__.py
ctrlaltdata/analysis.py
ctrlaltdata/api.py
ctrlaltdata/config.py
ctrlaltdata/database.py
ctrlaltdata/panel_constructors.py
ctrlaltdata/resource.py
ctrlaltdata/units.py
ctrlaltdata/util.py
ctrlaltdata/qad/__init__.py
ctrlaltdata/qad/api.py
ctrlaltdata/qad/qad.py
ctrlaltdata/tests/__init__.py
ctrlaltdata/tests/unit/__init__.py
ctrlaltdata/tests/unit/test_analysis.py
ctrlaltdata/tests/unit/test_api.py
ctrlaltdata/tests/unit/test_database.py
ctrlaltdata/tests/unit/test_units.py
ctrlaltdata/tests/unit/test_qad/__init__.py
ctrlaltdata/tests/unit/test_qad/test_api.py
ctrlaltdata/tests/unit/test_qad/test_qad.py
ctrlaltdata-0.1.dist-info/LICENSE
ctrlaltdata-0.1.dist-info/METADATA
ctrlaltdata-0.1.dist-info/WHEEL
ctrlaltdata-0.1.dist-info/top_level.txt
ctrlaltdata-0.1.dist-info/RECORD
