Metadata-Version: 2.1
Name: ctrlaltdata
Version: 0.1
Summary: A package for working with alternative data sets in a finance setting.
Author-email: Barclays Research Data Science <researchdatagovernance@barclayscorp.com>
License: Apache License
Project-URL: Homepage, https://github.com/barclays/research_data_sciene
Project-URL: Bug Tracker, https://github.com/pypa/research_data_science/issues
Classifier: Programming Language :: Python :: 3
Classifier: License :: OSI Approved :: MIT License
Classifier: Operating System :: OS Independent
Requires-Python: >=3.6
License-File: LICENSE
Requires-Dist: moneypandas
Requires-Dist: numpy
Requires-Dist: pandas
Requires-Dist: pyodbc
Requires-Dist: tqdm
Requires-Dist: pyspark
Requires-Dist: python-stdnum
Requires-Dist: money
